{
  "name": "피드백 수집 및 시너지 보정",
  "nodes": [
    {
      "parameters": {
        "httpMethod": "POST",
        "path": "feedback",
        "responseMode": "responseNode",
        "options": {}
      },
      "id": "feedback-webhook",
      "name": "피드백 Webhook",
      "type": "n8n-nodes-base.webhook",
      "typeVersion": 2,
      "position": [250, 300]
    },
    {
      "parameters": {
        "jsCode": "const data = $input.first().json;\n\n// 피드백 검증\nif (!data.automation_id || data.rating === undefined) {\n  throw new Error('automation_id와 rating은 필수입니다.');\n}\n\n// rating: 1 (긍정), -1 (부정)\nconst rating = data.rating > 0 ? 1 : -1;\n\n// 시너지율 조정 계산\n// 긍정: +2%, 부정: -5%\nconst synergyAdjustment = rating === 1 ? 0.02 : -0.05;\n\nreturn [{\n  json: {\n    automation_id: data.automation_id,\n    rating,\n    comment: data.comment || '',\n    synergy_adjustment: synergyAdjustment,\n    processed_at: new Date().toISOString()\n  }\n}];"
      },
      "id": "process-feedback",
      "name": "피드백 처리",
      "type": "n8n-nodes-base.code",
      "typeVersion": 2,
      "position": [450, 300]
    },
    {
      "parameters": {
        "method": "POST",
        "url": "={{$env.AUTUS_API_URL}}/api/feedback",
        "sendBody": true,
        "bodyParameters": {
          "parameters": [
            {
              "name": "automation_id",
              "value": "={{ $json.automation_id }}"
            },
            {
              "name": "rating",
              "value": "={{ $json.rating }}"
            },
            {
              "name": "comment",
              "value": "={{ $json.comment }}"
            },
            {
              "name": "synergy_adjustment",
              "value": "={{ $json.synergy_adjustment }}"
            }
          ]
        },
        "options": {}
      },
      "id": "save-feedback",
      "name": "피드백 저장",
      "type": "n8n-nodes-base.httpRequest",
      "typeVersion": 4.2,
      "position": [650, 300]
    },
    {
      "parameters": {
        "method": "PATCH",
        "url": "={{$env.AUTUS_API_URL}}/api/automations/{{ $json.automation_id }}/synergy",
        "sendBody": true,
        "bodyParameters": {
          "parameters": [
            {
              "name": "adjustment",
              "value": "={{ $json.synergy_adjustment }}"
            }
          ]
        },
        "options": {}
      },
      "id": "update-synergy",
      "name": "시너지율 업데이트",
      "type": "n8n-nodes-base.httpRequest",
      "typeVersion": 4.2,
      "position": [850, 300]
    },
    {
      "parameters": {
        "conditions": {
          "options": {
            "caseSensitive": true,
            "leftValue": "",
            "typeValidation": "strict"
          },
          "conditions": [
            {
              "id": "rating-check",
              "leftValue": "={{ $json.rating }}",
              "rightValue": -1,
              "operator": {
                "type": "number",
                "operation": "equals"
              }
            }
          ]
        }
      },
      "id": "check-negative",
      "name": "부정 피드백?",
      "type": "n8n-nodes-base.if",
      "typeVersion": 2,
      "position": [1050, 300]
    },
    {
      "parameters": {
        "channel": "#autus-alerts",
        "text": "=⚠️ 부정 피드백 수신\n\n*자동화 ID:* {{ $json.automation_id }}\n*코멘트:* {{ $json.comment }}\n*시너지 조정:* {{ $json.synergy_adjustment }}",
        "otherOptions": {}
      },
      "id": "slack-alert",
      "name": "Slack 경고",
      "type": "n8n-nodes-base.slack",
      "typeVersion": 2.2,
      "position": [1250, 200]
    },
    {
      "parameters": {
        "respondWith": "json",
        "responseBody": "={{ { success: true, message: '피드백 처리 완료', synergy_adjustment: $json.synergy_adjustment } }}",
        "options": {}
      },
      "id": "respond",
      "name": "응답 반환",
      "type": "n8n-nodes-base.respondToWebhook",
      "typeVersion": 1.1,
      "position": [1250, 400]
    }
  ],
  "connections": {
    "피드백 Webhook": {
      "main": [
        [
          {
            "node": "피드백 처리",
            "type": "main",
            "index": 0
          }
        ]
      ]
    },
    "피드백 처리": {
      "main": [
        [
          {
            "node": "피드백 저장",
            "type": "main",
            "index": 0
          }
        ]
      ]
    },
    "피드백 저장": {
      "main": [
        [
          {
            "node": "시너지율 업데이트",
            "type": "main",
            "index": 0
          }
        ]
      ]
    },
    "시너지율 업데이트": {
      "main": [
        [
          {
            "node": "부정 피드백?",
            "type": "main",
            "index": 0
          }
        ]
      ]
    },
    "부정 피드백?": {
      "main": [
        [
          {
            "node": "Slack 경고",
            "type": "main",
            "index": 0
          }
        ],
        [
          {
            "node": "응답 반환",
            "type": "main",
            "index": 0
          }
        ]
      ]
    },
    "Slack 경고": {
      "main": [
        [
          {
            "node": "응답 반환",
            "type": "main",
            "index": 0
          }
        ]
      ]
    }
  },
  "active": false,
  "settings": {
    "executionOrder": "v1"
  },
  "tags": [
    {
      "name": "autus",
      "id": "autus-tag"
    }
  ]
}

{
  "name": "피드백 수집 및 시너지 보정",
  "nodes": [
    {
      "parameters": {
        "httpMethod": "POST",
        "path": "feedback",
        "responseMode": "responseNode",
        "options": {}
      },
      "id": "feedback-webhook",
      "name": "피드백 Webhook",
      "type": "n8n-nodes-base.webhook",
      "typeVersion": 2,
      "position": [250, 300]
    },
    {
      "parameters": {
        "jsCode": "const data = $input.first().json;\n\n// 피드백 검증\nif (!data.automation_id || data.rating === undefined) {\n  throw new Error('automation_id와 rating은 필수입니다.');\n}\n\n// rating: 1 (긍정), -1 (부정)\nconst rating = data.rating > 0 ? 1 : -1;\n\n// 시너지율 조정 계산\n// 긍정: +2%, 부정: -5%\nconst synergyAdjustment = rating === 1 ? 0.02 : -0.05;\n\nreturn [{\n  json: {\n    automation_id: data.automation_id,\n    rating,\n    comment: data.comment || '',\n    synergy_adjustment: synergyAdjustment,\n    processed_at: new Date().toISOString()\n  }\n}];"
      },
      "id": "process-feedback",
      "name": "피드백 처리",
      "type": "n8n-nodes-base.code",
      "typeVersion": 2,
      "position": [450, 300]
    },
    {
      "parameters": {
        "method": "POST",
        "url": "={{$env.AUTUS_API_URL}}/api/feedback",
        "sendBody": true,
        "bodyParameters": {
          "parameters": [
            {
              "name": "automation_id",
              "value": "={{ $json.automation_id }}"
            },
            {
              "name": "rating",
              "value": "={{ $json.rating }}"
            },
            {
              "name": "comment",
              "value": "={{ $json.comment }}"
            },
            {
              "name": "synergy_adjustment",
              "value": "={{ $json.synergy_adjustment }}"
            }
          ]
        },
        "options": {}
      },
      "id": "save-feedback",
      "name": "피드백 저장",
      "type": "n8n-nodes-base.httpRequest",
      "typeVersion": 4.2,
      "position": [650, 300]
    },
    {
      "parameters": {
        "method": "PATCH",
        "url": "={{$env.AUTUS_API_URL}}/api/automations/{{ $json.automation_id }}/synergy",
        "sendBody": true,
        "bodyParameters": {
          "parameters": [
            {
              "name": "adjustment",
              "value": "={{ $json.synergy_adjustment }}"
            }
          ]
        },
        "options": {}
      },
      "id": "update-synergy",
      "name": "시너지율 업데이트",
      "type": "n8n-nodes-base.httpRequest",
      "typeVersion": 4.2,
      "position": [850, 300]
    },
    {
      "parameters": {
        "conditions": {
          "options": {
            "caseSensitive": true,
            "leftValue": "",
            "typeValidation": "strict"
          },
          "conditions": [
            {
              "id": "rating-check",
              "leftValue": "={{ $json.rating }}",
              "rightValue": -1,
              "operator": {
                "type": "number",
                "operation": "equals"
              }
            }
          ]
        }
      },
      "id": "check-negative",
      "name": "부정 피드백?",
      "type": "n8n-nodes-base.if",
      "typeVersion": 2,
      "position": [1050, 300]
    },
    {
      "parameters": {
        "channel": "#autus-alerts",
        "text": "=⚠️ 부정 피드백 수신\n\n*자동화 ID:* {{ $json.automation_id }}\n*코멘트:* {{ $json.comment }}\n*시너지 조정:* {{ $json.synergy_adjustment }}",
        "otherOptions": {}
      },
      "id": "slack-alert",
      "name": "Slack 경고",
      "type": "n8n-nodes-base.slack",
      "typeVersion": 2.2,
      "position": [1250, 200]
    },
    {
      "parameters": {
        "respondWith": "json",
        "responseBody": "={{ { success: true, message: '피드백 처리 완료', synergy_adjustment: $json.synergy_adjustment } }}",
        "options": {}
      },
      "id": "respond",
      "name": "응답 반환",
      "type": "n8n-nodes-base.respondToWebhook",
      "typeVersion": 1.1,
      "position": [1250, 400]
    }
  ],
  "connections": {
    "피드백 Webhook": {
      "main": [
        [
          {
            "node": "피드백 처리",
            "type": "main",
            "index": 0
          }
        ]
      ]
    },
    "피드백 처리": {
      "main": [
        [
          {
            "node": "피드백 저장",
            "type": "main",
            "index": 0
          }
        ]
      ]
    },
    "피드백 저장": {
      "main": [
        [
          {
            "node": "시너지율 업데이트",
            "type": "main",
            "index": 0
          }
        ]
      ]
    },
    "시너지율 업데이트": {
      "main": [
        [
          {
            "node": "부정 피드백?",
            "type": "main",
            "index": 0
          }
        ]
      ]
    },
    "부정 피드백?": {
      "main": [
        [
          {
            "node": "Slack 경고",
            "type": "main",
            "index": 0
          }
        ],
        [
          {
            "node": "응답 반환",
            "type": "main",
            "index": 0
          }
        ]
      ]
    },
    "Slack 경고": {
      "main": [
        [
          {
            "node": "응답 반환",
            "type": "main",
            "index": 0
          }
        ]
      ]
    }
  },
  "active": false,
  "settings": {
    "executionOrder": "v1"
  },
  "tags": [
    {
      "name": "autus",
      "id": "autus-tag"
    }
  ]
}

{
  "name": "피드백 수집 및 시너지 보정",
  "nodes": [
    {
      "parameters": {
        "httpMethod": "POST",
        "path": "feedback",
        "responseMode": "responseNode",
        "options": {}
      },
      "id": "feedback-webhook",
      "name": "피드백 Webhook",
      "type": "n8n-nodes-base.webhook",
      "typeVersion": 2,
      "position": [250, 300]
    },
    {
      "parameters": {
        "jsCode": "const data = $input.first().json;\n\n// 피드백 검증\nif (!data.automation_id || data.rating === undefined) {\n  throw new Error('automation_id와 rating은 필수입니다.');\n}\n\n// rating: 1 (긍정), -1 (부정)\nconst rating = data.rating > 0 ? 1 : -1;\n\n// 시너지율 조정 계산\n// 긍정: +2%, 부정: -5%\nconst synergyAdjustment = rating === 1 ? 0.02 : -0.05;\n\nreturn [{\n  json: {\n    automation_id: data.automation_id,\n    rating,\n    comment: data.comment || '',\n    synergy_adjustment: synergyAdjustment,\n    processed_at: new Date().toISOString()\n  }\n}];"
      },
      "id": "process-feedback",
      "name": "피드백 처리",
      "type": "n8n-nodes-base.code",
      "typeVersion": 2,
      "position": [450, 300]
    },
    {
      "parameters": {
        "method": "POST",
        "url": "={{$env.AUTUS_API_URL}}/api/feedback",
        "sendBody": true,
        "bodyParameters": {
          "parameters": [
            {
              "name": "automation_id",
              "value": "={{ $json.automation_id }}"
            },
            {
              "name": "rating",
              "value": "={{ $json.rating }}"
            },
            {
              "name": "comment",
              "value": "={{ $json.comment }}"
            },
            {
              "name": "synergy_adjustment",
              "value": "={{ $json.synergy_adjustment }}"
            }
          ]
        },
        "options": {}
      },
      "id": "save-feedback",
      "name": "피드백 저장",
      "type": "n8n-nodes-base.httpRequest",
      "typeVersion": 4.2,
      "position": [650, 300]
    },
    {
      "parameters": {
        "method": "PATCH",
        "url": "={{$env.AUTUS_API_URL}}/api/automations/{{ $json.automation_id }}/synergy",
        "sendBody": true,
        "bodyParameters": {
          "parameters": [
            {
              "name": "adjustment",
              "value": "={{ $json.synergy_adjustment }}"
            }
          ]
        },
        "options": {}
      },
      "id": "update-synergy",
      "name": "시너지율 업데이트",
      "type": "n8n-nodes-base.httpRequest",
      "typeVersion": 4.2,
      "position": [850, 300]
    },
    {
      "parameters": {
        "conditions": {
          "options": {
            "caseSensitive": true,
            "leftValue": "",
            "typeValidation": "strict"
          },
          "conditions": [
            {
              "id": "rating-check",
              "leftValue": "={{ $json.rating }}",
              "rightValue": -1,
              "operator": {
                "type": "number",
                "operation": "equals"
              }
            }
          ]
        }
      },
      "id": "check-negative",
      "name": "부정 피드백?",
      "type": "n8n-nodes-base.if",
      "typeVersion": 2,
      "position": [1050, 300]
    },
    {
      "parameters": {
        "channel": "#autus-alerts",
        "text": "=⚠️ 부정 피드백 수신\n\n*자동화 ID:* {{ $json.automation_id }}\n*코멘트:* {{ $json.comment }}\n*시너지 조정:* {{ $json.synergy_adjustment }}",
        "otherOptions": {}
      },
      "id": "slack-alert",
      "name": "Slack 경고",
      "type": "n8n-nodes-base.slack",
      "typeVersion": 2.2,
      "position": [1250, 200]
    },
    {
      "parameters": {
        "respondWith": "json",
        "responseBody": "={{ { success: true, message: '피드백 처리 완료', synergy_adjustment: $json.synergy_adjustment } }}",
        "options": {}
      },
      "id": "respond",
      "name": "응답 반환",
      "type": "n8n-nodes-base.respondToWebhook",
      "typeVersion": 1.1,
      "position": [1250, 400]
    }
  ],
  "connections": {
    "피드백 Webhook": {
      "main": [
        [
          {
            "node": "피드백 처리",
            "type": "main",
            "index": 0
          }
        ]
      ]
    },
    "피드백 처리": {
      "main": [
        [
          {
            "node": "피드백 저장",
            "type": "main",
            "index": 0
          }
        ]
      ]
    },
    "피드백 저장": {
      "main": [
        [
          {
            "node": "시너지율 업데이트",
            "type": "main",
            "index": 0
          }
        ]
      ]
    },
    "시너지율 업데이트": {
      "main": [
        [
          {
            "node": "부정 피드백?",
            "type": "main",
            "index": 0
          }
        ]
      ]
    },
    "부정 피드백?": {
      "main": [
        [
          {
            "node": "Slack 경고",
            "type": "main",
            "index": 0
          }
        ],
        [
          {
            "node": "응답 반환",
            "type": "main",
            "index": 0
          }
        ]
      ]
    },
    "Slack 경고": {
      "main": [
        [
          {
            "node": "응답 반환",
            "type": "main",
            "index": 0
          }
        ]
      ]
    }
  },
  "active": false,
  "settings": {
    "executionOrder": "v1"
  },
  "tags": [
    {
      "name": "autus",
      "id": "autus-tag"
    }
  ]
}

{
  "name": "피드백 수집 및 시너지 보정",
  "nodes": [
    {
      "parameters": {
        "httpMethod": "POST",
        "path": "feedback",
        "responseMode": "responseNode",
        "options": {}
      },
      "id": "feedback-webhook",
      "name": "피드백 Webhook",
      "type": "n8n-nodes-base.webhook",
      "typeVersion": 2,
      "position": [250, 300]
    },
    {
      "parameters": {
        "jsCode": "const data = $input.first().json;\n\n// 피드백 검증\nif (!data.automation_id || data.rating === undefined) {\n  throw new Error('automation_id와 rating은 필수입니다.');\n}\n\n// rating: 1 (긍정), -1 (부정)\nconst rating = data.rating > 0 ? 1 : -1;\n\n// 시너지율 조정 계산\n// 긍정: +2%, 부정: -5%\nconst synergyAdjustment = rating === 1 ? 0.02 : -0.05;\n\nreturn [{\n  json: {\n    automation_id: data.automation_id,\n    rating,\n    comment: data.comment || '',\n    synergy_adjustment: synergyAdjustment,\n    processed_at: new Date().toISOString()\n  }\n}];"
      },
      "id": "process-feedback",
      "name": "피드백 처리",
      "type": "n8n-nodes-base.code",
      "typeVersion": 2,
      "position": [450, 300]
    },
    {
      "parameters": {
        "method": "POST",
        "url": "={{$env.AUTUS_API_URL}}/api/feedback",
        "sendBody": true,
        "bodyParameters": {
          "parameters": [
            {
              "name": "automation_id",
              "value": "={{ $json.automation_id }}"
            },
            {
              "name": "rating",
              "value": "={{ $json.rating }}"
            },
            {
              "name": "comment",
              "value": "={{ $json.comment }}"
            },
            {
              "name": "synergy_adjustment",
              "value": "={{ $json.synergy_adjustment }}"
            }
          ]
        },
        "options": {}
      },
      "id": "save-feedback",
      "name": "피드백 저장",
      "type": "n8n-nodes-base.httpRequest",
      "typeVersion": 4.2,
      "position": [650, 300]
    },
    {
      "parameters": {
        "method": "PATCH",
        "url": "={{$env.AUTUS_API_URL}}/api/automations/{{ $json.automation_id }}/synergy",
        "sendBody": true,
        "bodyParameters": {
          "parameters": [
            {
              "name": "adjustment",
              "value": "={{ $json.synergy_adjustment }}"
            }
          ]
        },
        "options": {}
      },
      "id": "update-synergy",
      "name": "시너지율 업데이트",
      "type": "n8n-nodes-base.httpRequest",
      "typeVersion": 4.2,
      "position": [850, 300]
    },
    {
      "parameters": {
        "conditions": {
          "options": {
            "caseSensitive": true,
            "leftValue": "",
            "typeValidation": "strict"
          },
          "conditions": [
            {
              "id": "rating-check",
              "leftValue": "={{ $json.rating }}",
              "rightValue": -1,
              "operator": {
                "type": "number",
                "operation": "equals"
              }
            }
          ]
        }
      },
      "id": "check-negative",
      "name": "부정 피드백?",
      "type": "n8n-nodes-base.if",
      "typeVersion": 2,
      "position": [1050, 300]
    },
    {
      "parameters": {
        "channel": "#autus-alerts",
        "text": "=⚠️ 부정 피드백 수신\n\n*자동화 ID:* {{ $json.automation_id }}\n*코멘트:* {{ $json.comment }}\n*시너지 조정:* {{ $json.synergy_adjustment }}",
        "otherOptions": {}
      },
      "id": "slack-alert",
      "name": "Slack 경고",
      "type": "n8n-nodes-base.slack",
      "typeVersion": 2.2,
      "position": [1250, 200]
    },
    {
      "parameters": {
        "respondWith": "json",
        "responseBody": "={{ { success: true, message: '피드백 처리 완료', synergy_adjustment: $json.synergy_adjustment } }}",
        "options": {}
      },
      "id": "respond",
      "name": "응답 반환",
      "type": "n8n-nodes-base.respondToWebhook",
      "typeVersion": 1.1,
      "position": [1250, 400]
    }
  ],
  "connections": {
    "피드백 Webhook": {
      "main": [
        [
          {
            "node": "피드백 처리",
            "type": "main",
            "index": 0
          }
        ]
      ]
    },
    "피드백 처리": {
      "main": [
        [
          {
            "node": "피드백 저장",
            "type": "main",
            "index": 0
          }
        ]
      ]
    },
    "피드백 저장": {
      "main": [
        [
          {
            "node": "시너지율 업데이트",
            "type": "main",
            "index": 0
          }
        ]
      ]
    },
    "시너지율 업데이트": {
      "main": [
        [
          {
            "node": "부정 피드백?",
            "type": "main",
            "index": 0
          }
        ]
      ]
    },
    "부정 피드백?": {
      "main": [
        [
          {
            "node": "Slack 경고",
            "type": "main",
            "index": 0
          }
        ],
        [
          {
            "node": "응답 반환",
            "type": "main",
            "index": 0
          }
        ]
      ]
    },
    "Slack 경고": {
      "main": [
        [
          {
            "node": "응답 반환",
            "type": "main",
            "index": 0
          }
        ]
      ]
    }
  },
  "active": false,
  "settings": {
    "executionOrder": "v1"
  },
  "tags": [
    {
      "name": "autus",
      "id": "autus-tag"
    }
  ]
}

{
  "name": "피드백 수집 및 시너지 보정",
  "nodes": [
    {
      "parameters": {
        "httpMethod": "POST",
        "path": "feedback",
        "responseMode": "responseNode",
        "options": {}
      },
      "id": "feedback-webhook",
      "name": "피드백 Webhook",
      "type": "n8n-nodes-base.webhook",
      "typeVersion": 2,
      "position": [250, 300]
    },
    {
      "parameters": {
        "jsCode": "const data = $input.first().json;\n\n// 피드백 검증\nif (!data.automation_id || data.rating === undefined) {\n  throw new Error('automation_id와 rating은 필수입니다.');\n}\n\n// rating: 1 (긍정), -1 (부정)\nconst rating = data.rating > 0 ? 1 : -1;\n\n// 시너지율 조정 계산\n// 긍정: +2%, 부정: -5%\nconst synergyAdjustment = rating === 1 ? 0.02 : -0.05;\n\nreturn [{\n  json: {\n    automation_id: data.automation_id,\n    rating,\n    comment: data.comment || '',\n    synergy_adjustment: synergyAdjustment,\n    processed_at: new Date().toISOString()\n  }\n}];"
      },
      "id": "process-feedback",
      "name": "피드백 처리",
      "type": "n8n-nodes-base.code",
      "typeVersion": 2,
      "position": [450, 300]
    },
    {
      "parameters": {
        "method": "POST",
        "url": "={{$env.AUTUS_API_URL}}/api/feedback",
        "sendBody": true,
        "bodyParameters": {
          "parameters": [
            {
              "name": "automation_id",
              "value": "={{ $json.automation_id }}"
            },
            {
              "name": "rating",
              "value": "={{ $json.rating }}"
            },
            {
              "name": "comment",
              "value": "={{ $json.comment }}"
            },
            {
              "name": "synergy_adjustment",
              "value": "={{ $json.synergy_adjustment }}"
            }
          ]
        },
        "options": {}
      },
      "id": "save-feedback",
      "name": "피드백 저장",
      "type": "n8n-nodes-base.httpRequest",
      "typeVersion": 4.2,
      "position": [650, 300]
    },
    {
      "parameters": {
        "method": "PATCH",
        "url": "={{$env.AUTUS_API_URL}}/api/automations/{{ $json.automation_id }}/synergy",
        "sendBody": true,
        "bodyParameters": {
          "parameters": [
            {
              "name": "adjustment",
              "value": "={{ $json.synergy_adjustment }}"
            }
          ]
        },
        "options": {}
      },
      "id": "update-synergy",
      "name": "시너지율 업데이트",
      "type": "n8n-nodes-base.httpRequest",
      "typeVersion": 4.2,
      "position": [850, 300]
    },
    {
      "parameters": {
        "conditions": {
          "options": {
            "caseSensitive": true,
            "leftValue": "",
            "typeValidation": "strict"
          },
          "conditions": [
            {
              "id": "rating-check",
              "leftValue": "={{ $json.rating }}",
              "rightValue": -1,
              "operator": {
                "type": "number",
                "operation": "equals"
              }
            }
          ]
        }
      },
      "id": "check-negative",
      "name": "부정 피드백?",
      "type": "n8n-nodes-base.if",
      "typeVersion": 2,
      "position": [1050, 300]
    },
    {
      "parameters": {
        "channel": "#autus-alerts",
        "text": "=⚠️ 부정 피드백 수신\n\n*자동화 ID:* {{ $json.automation_id }}\n*코멘트:* {{ $json.comment }}\n*시너지 조정:* {{ $json.synergy_adjustment }}",
        "otherOptions": {}
      },
      "id": "slack-alert",
      "name": "Slack 경고",
      "type": "n8n-nodes-base.slack",
      "typeVersion": 2.2,
      "position": [1250, 200]
    },
    {
      "parameters": {
        "respondWith": "json",
        "responseBody": "={{ { success: true, message: '피드백 처리 완료', synergy_adjustment: $json.synergy_adjustment } }}",
        "options": {}
      },
      "id": "respond",
      "name": "응답 반환",
      "type": "n8n-nodes-base.respondToWebhook",
      "typeVersion": 1.1,
      "position": [1250, 400]
    }
  ],
  "connections": {
    "피드백 Webhook": {
      "main": [
        [
          {
            "node": "피드백 처리",
            "type": "main",
            "index": 0
          }
        ]
      ]
    },
    "피드백 처리": {
      "main": [
        [
          {
            "node": "피드백 저장",
            "type": "main",
            "index": 0
          }
        ]
      ]
    },
    "피드백 저장": {
      "main": [
        [
          {
            "node": "시너지율 업데이트",
            "type": "main",
            "index": 0
          }
        ]
      ]
    },
    "시너지율 업데이트": {
      "main": [
        [
          {
            "node": "부정 피드백?",
            "type": "main",
            "index": 0
          }
        ]
      ]
    },
    "부정 피드백?": {
      "main": [
        [
          {
            "node": "Slack 경고",
            "type": "main",
            "index": 0
          }
        ],
        [
          {
            "node": "응답 반환",
            "type": "main",
            "index": 0
          }
        ]
      ]
    },
    "Slack 경고": {
      "main": [
        [
          {
            "node": "응답 반환",
            "type": "main",
            "index": 0
          }
        ]
      ]
    }
  },
  "active": false,
  "settings": {
    "executionOrder": "v1"
  },
  "tags": [
    {
      "name": "autus",
      "id": "autus-tag"
    }
  ]
}











{
  "name": "피드백 수집 및 시너지 보정",
  "nodes": [
    {
      "parameters": {
        "httpMethod": "POST",
        "path": "feedback",
        "responseMode": "responseNode",
        "options": {}
      },
      "id": "feedback-webhook",
      "name": "피드백 Webhook",
      "type": "n8n-nodes-base.webhook",
      "typeVersion": 2,
      "position": [250, 300]
    },
    {
      "parameters": {
        "jsCode": "const data = $input.first().json;\n\n// 피드백 검증\nif (!data.automation_id || data.rating === undefined) {\n  throw new Error('automation_id와 rating은 필수입니다.');\n}\n\n// rating: 1 (긍정), -1 (부정)\nconst rating = data.rating > 0 ? 1 : -1;\n\n// 시너지율 조정 계산\n// 긍정: +2%, 부정: -5%\nconst synergyAdjustment = rating === 1 ? 0.02 : -0.05;\n\nreturn [{\n  json: {\n    automation_id: data.automation_id,\n    rating,\n    comment: data.comment || '',\n    synergy_adjustment: synergyAdjustment,\n    processed_at: new Date().toISOString()\n  }\n}];"
      },
      "id": "process-feedback",
      "name": "피드백 처리",
      "type": "n8n-nodes-base.code",
      "typeVersion": 2,
      "position": [450, 300]
    },
    {
      "parameters": {
        "method": "POST",
        "url": "={{$env.AUTUS_API_URL}}/api/feedback",
        "sendBody": true,
        "bodyParameters": {
          "parameters": [
            {
              "name": "automation_id",
              "value": "={{ $json.automation_id }}"
            },
            {
              "name": "rating",
              "value": "={{ $json.rating }}"
            },
            {
              "name": "comment",
              "value": "={{ $json.comment }}"
            },
            {
              "name": "synergy_adjustment",
              "value": "={{ $json.synergy_adjustment }}"
            }
          ]
        },
        "options": {}
      },
      "id": "save-feedback",
      "name": "피드백 저장",
      "type": "n8n-nodes-base.httpRequest",
      "typeVersion": 4.2,
      "position": [650, 300]
    },
    {
      "parameters": {
        "method": "PATCH",
        "url": "={{$env.AUTUS_API_URL}}/api/automations/{{ $json.automation_id }}/synergy",
        "sendBody": true,
        "bodyParameters": {
          "parameters": [
            {
              "name": "adjustment",
              "value": "={{ $json.synergy_adjustment }}"
            }
          ]
        },
        "options": {}
      },
      "id": "update-synergy",
      "name": "시너지율 업데이트",
      "type": "n8n-nodes-base.httpRequest",
      "typeVersion": 4.2,
      "position": [850, 300]
    },
    {
      "parameters": {
        "conditions": {
          "options": {
            "caseSensitive": true,
            "leftValue": "",
            "typeValidation": "strict"
          },
          "conditions": [
            {
              "id": "rating-check",
              "leftValue": "={{ $json.rating }}",
              "rightValue": -1,
              "operator": {
                "type": "number",
                "operation": "equals"
              }
            }
          ]
        }
      },
      "id": "check-negative",
      "name": "부정 피드백?",
      "type": "n8n-nodes-base.if",
      "typeVersion": 2,
      "position": [1050, 300]
    },
    {
      "parameters": {
        "channel": "#autus-alerts",
        "text": "=⚠️ 부정 피드백 수신\n\n*자동화 ID:* {{ $json.automation_id }}\n*코멘트:* {{ $json.comment }}\n*시너지 조정:* {{ $json.synergy_adjustment }}",
        "otherOptions": {}
      },
      "id": "slack-alert",
      "name": "Slack 경고",
      "type": "n8n-nodes-base.slack",
      "typeVersion": 2.2,
      "position": [1250, 200]
    },
    {
      "parameters": {
        "respondWith": "json",
        "responseBody": "={{ { success: true, message: '피드백 처리 완료', synergy_adjustment: $json.synergy_adjustment } }}",
        "options": {}
      },
      "id": "respond",
      "name": "응답 반환",
      "type": "n8n-nodes-base.respondToWebhook",
      "typeVersion": 1.1,
      "position": [1250, 400]
    }
  ],
  "connections": {
    "피드백 Webhook": {
      "main": [
        [
          {
            "node": "피드백 처리",
            "type": "main",
            "index": 0
          }
        ]
      ]
    },
    "피드백 처리": {
      "main": [
        [
          {
            "node": "피드백 저장",
            "type": "main",
            "index": 0
          }
        ]
      ]
    },
    "피드백 저장": {
      "main": [
        [
          {
            "node": "시너지율 업데이트",
            "type": "main",
            "index": 0
          }
        ]
      ]
    },
    "시너지율 업데이트": {
      "main": [
        [
          {
            "node": "부정 피드백?",
            "type": "main",
            "index": 0
          }
        ]
      ]
    },
    "부정 피드백?": {
      "main": [
        [
          {
            "node": "Slack 경고",
            "type": "main",
            "index": 0
          }
        ],
        [
          {
            "node": "응답 반환",
            "type": "main",
            "index": 0
          }
        ]
      ]
    },
    "Slack 경고": {
      "main": [
        [
          {
            "node": "응답 반환",
            "type": "main",
            "index": 0
          }
        ]
      ]
    }
  },
  "active": false,
  "settings": {
    "executionOrder": "v1"
  },
  "tags": [
    {
      "name": "autus",
      "id": "autus-tag"
    }
  ]
}

{
  "name": "피드백 수집 및 시너지 보정",
  "nodes": [
    {
      "parameters": {
        "httpMethod": "POST",
        "path": "feedback",
        "responseMode": "responseNode",
        "options": {}
      },
      "id": "feedback-webhook",
      "name": "피드백 Webhook",
      "type": "n8n-nodes-base.webhook",
      "typeVersion": 2,
      "position": [250, 300]
    },
    {
      "parameters": {
        "jsCode": "const data = $input.first().json;\n\n// 피드백 검증\nif (!data.automation_id || data.rating === undefined) {\n  throw new Error('automation_id와 rating은 필수입니다.');\n}\n\n// rating: 1 (긍정), -1 (부정)\nconst rating = data.rating > 0 ? 1 : -1;\n\n// 시너지율 조정 계산\n// 긍정: +2%, 부정: -5%\nconst synergyAdjustment = rating === 1 ? 0.02 : -0.05;\n\nreturn [{\n  json: {\n    automation_id: data.automation_id,\n    rating,\n    comment: data.comment || '',\n    synergy_adjustment: synergyAdjustment,\n    processed_at: new Date().toISOString()\n  }\n}];"
      },
      "id": "process-feedback",
      "name": "피드백 처리",
      "type": "n8n-nodes-base.code",
      "typeVersion": 2,
      "position": [450, 300]
    },
    {
      "parameters": {
        "method": "POST",
        "url": "={{$env.AUTUS_API_URL}}/api/feedback",
        "sendBody": true,
        "bodyParameters": {
          "parameters": [
            {
              "name": "automation_id",
              "value": "={{ $json.automation_id }}"
            },
            {
              "name": "rating",
              "value": "={{ $json.rating }}"
            },
            {
              "name": "comment",
              "value": "={{ $json.comment }}"
            },
            {
              "name": "synergy_adjustment",
              "value": "={{ $json.synergy_adjustment }}"
            }
          ]
        },
        "options": {}
      },
      "id": "save-feedback",
      "name": "피드백 저장",
      "type": "n8n-nodes-base.httpRequest",
      "typeVersion": 4.2,
      "position": [650, 300]
    },
    {
      "parameters": {
        "method": "PATCH",
        "url": "={{$env.AUTUS_API_URL}}/api/automations/{{ $json.automation_id }}/synergy",
        "sendBody": true,
        "bodyParameters": {
          "parameters": [
            {
              "name": "adjustment",
              "value": "={{ $json.synergy_adjustment }}"
            }
          ]
        },
        "options": {}
      },
      "id": "update-synergy",
      "name": "시너지율 업데이트",
      "type": "n8n-nodes-base.httpRequest",
      "typeVersion": 4.2,
      "position": [850, 300]
    },
    {
      "parameters": {
        "conditions": {
          "options": {
            "caseSensitive": true,
            "leftValue": "",
            "typeValidation": "strict"
          },
          "conditions": [
            {
              "id": "rating-check",
              "leftValue": "={{ $json.rating }}",
              "rightValue": -1,
              "operator": {
                "type": "number",
                "operation": "equals"
              }
            }
          ]
        }
      },
      "id": "check-negative",
      "name": "부정 피드백?",
      "type": "n8n-nodes-base.if",
      "typeVersion": 2,
      "position": [1050, 300]
    },
    {
      "parameters": {
        "channel": "#autus-alerts",
        "text": "=⚠️ 부정 피드백 수신\n\n*자동화 ID:* {{ $json.automation_id }}\n*코멘트:* {{ $json.comment }}\n*시너지 조정:* {{ $json.synergy_adjustment }}",
        "otherOptions": {}
      },
      "id": "slack-alert",
      "name": "Slack 경고",
      "type": "n8n-nodes-base.slack",
      "typeVersion": 2.2,
      "position": [1250, 200]
    },
    {
      "parameters": {
        "respondWith": "json",
        "responseBody": "={{ { success: true, message: '피드백 처리 완료', synergy_adjustment: $json.synergy_adjustment } }}",
        "options": {}
      },
      "id": "respond",
      "name": "응답 반환",
      "type": "n8n-nodes-base.respondToWebhook",
      "typeVersion": 1.1,
      "position": [1250, 400]
    }
  ],
  "connections": {
    "피드백 Webhook": {
      "main": [
        [
          {
            "node": "피드백 처리",
            "type": "main",
            "index": 0
          }
        ]
      ]
    },
    "피드백 처리": {
      "main": [
        [
          {
            "node": "피드백 저장",
            "type": "main",
            "index": 0
          }
        ]
      ]
    },
    "피드백 저장": {
      "main": [
        [
          {
            "node": "시너지율 업데이트",
            "type": "main",
            "index": 0
          }
        ]
      ]
    },
    "시너지율 업데이트": {
      "main": [
        [
          {
            "node": "부정 피드백?",
            "type": "main",
            "index": 0
          }
        ]
      ]
    },
    "부정 피드백?": {
      "main": [
        [
          {
            "node": "Slack 경고",
            "type": "main",
            "index": 0
          }
        ],
        [
          {
            "node": "응답 반환",
            "type": "main",
            "index": 0
          }
        ]
      ]
    },
    "Slack 경고": {
      "main": [
        [
          {
            "node": "응답 반환",
            "type": "main",
            "index": 0
          }
        ]
      ]
    }
  },
  "active": false,
  "settings": {
    "executionOrder": "v1"
  },
  "tags": [
    {
      "name": "autus",
      "id": "autus-tag"
    }
  ]
}

{
  "name": "피드백 수집 및 시너지 보정",
  "nodes": [
    {
      "parameters": {
        "httpMethod": "POST",
        "path": "feedback",
        "responseMode": "responseNode",
        "options": {}
      },
      "id": "feedback-webhook",
      "name": "피드백 Webhook",
      "type": "n8n-nodes-base.webhook",
      "typeVersion": 2,
      "position": [250, 300]
    },
    {
      "parameters": {
        "jsCode": "const data = $input.first().json;\n\n// 피드백 검증\nif (!data.automation_id || data.rating === undefined) {\n  throw new Error('automation_id와 rating은 필수입니다.');\n}\n\n// rating: 1 (긍정), -1 (부정)\nconst rating = data.rating > 0 ? 1 : -1;\n\n// 시너지율 조정 계산\n// 긍정: +2%, 부정: -5%\nconst synergyAdjustment = rating === 1 ? 0.02 : -0.05;\n\nreturn [{\n  json: {\n    automation_id: data.automation_id,\n    rating,\n    comment: data.comment || '',\n    synergy_adjustment: synergyAdjustment,\n    processed_at: new Date().toISOString()\n  }\n}];"
      },
      "id": "process-feedback",
      "name": "피드백 처리",
      "type": "n8n-nodes-base.code",
      "typeVersion": 2,
      "position": [450, 300]
    },
    {
      "parameters": {
        "method": "POST",
        "url": "={{$env.AUTUS_API_URL}}/api/feedback",
        "sendBody": true,
        "bodyParameters": {
          "parameters": [
            {
              "name": "automation_id",
              "value": "={{ $json.automation_id }}"
            },
            {
              "name": "rating",
              "value": "={{ $json.rating }}"
            },
            {
              "name": "comment",
              "value": "={{ $json.comment }}"
            },
            {
              "name": "synergy_adjustment",
              "value": "={{ $json.synergy_adjustment }}"
            }
          ]
        },
        "options": {}
      },
      "id": "save-feedback",
      "name": "피드백 저장",
      "type": "n8n-nodes-base.httpRequest",
      "typeVersion": 4.2,
      "position": [650, 300]
    },
    {
      "parameters": {
        "method": "PATCH",
        "url": "={{$env.AUTUS_API_URL}}/api/automations/{{ $json.automation_id }}/synergy",
        "sendBody": true,
        "bodyParameters": {
          "parameters": [
            {
              "name": "adjustment",
              "value": "={{ $json.synergy_adjustment }}"
            }
          ]
        },
        "options": {}
      },
      "id": "update-synergy",
      "name": "시너지율 업데이트",
      "type": "n8n-nodes-base.httpRequest",
      "typeVersion": 4.2,
      "position": [850, 300]
    },
    {
      "parameters": {
        "conditions": {
          "options": {
            "caseSensitive": true,
            "leftValue": "",
            "typeValidation": "strict"
          },
          "conditions": [
            {
              "id": "rating-check",
              "leftValue": "={{ $json.rating }}",
              "rightValue": -1,
              "operator": {
                "type": "number",
                "operation": "equals"
              }
            }
          ]
        }
      },
      "id": "check-negative",
      "name": "부정 피드백?",
      "type": "n8n-nodes-base.if",
      "typeVersion": 2,
      "position": [1050, 300]
    },
    {
      "parameters": {
        "channel": "#autus-alerts",
        "text": "=⚠️ 부정 피드백 수신\n\n*자동화 ID:* {{ $json.automation_id }}\n*코멘트:* {{ $json.comment }}\n*시너지 조정:* {{ $json.synergy_adjustment }}",
        "otherOptions": {}
      },
      "id": "slack-alert",
      "name": "Slack 경고",
      "type": "n8n-nodes-base.slack",
      "typeVersion": 2.2,
      "position": [1250, 200]
    },
    {
      "parameters": {
        "respondWith": "json",
        "responseBody": "={{ { success: true, message: '피드백 처리 완료', synergy_adjustment: $json.synergy_adjustment } }}",
        "options": {}
      },
      "id": "respond",
      "name": "응답 반환",
      "type": "n8n-nodes-base.respondToWebhook",
      "typeVersion": 1.1,
      "position": [1250, 400]
    }
  ],
  "connections": {
    "피드백 Webhook": {
      "main": [
        [
          {
            "node": "피드백 처리",
            "type": "main",
            "index": 0
          }
        ]
      ]
    },
    "피드백 처리": {
      "main": [
        [
          {
            "node": "피드백 저장",
            "type": "main",
            "index": 0
          }
        ]
      ]
    },
    "피드백 저장": {
      "main": [
        [
          {
            "node": "시너지율 업데이트",
            "type": "main",
            "index": 0
          }
        ]
      ]
    },
    "시너지율 업데이트": {
      "main": [
        [
          {
            "node": "부정 피드백?",
            "type": "main",
            "index": 0
          }
        ]
      ]
    },
    "부정 피드백?": {
      "main": [
        [
          {
            "node": "Slack 경고",
            "type": "main",
            "index": 0
          }
        ],
        [
          {
            "node": "응답 반환",
            "type": "main",
            "index": 0
          }
        ]
      ]
    },
    "Slack 경고": {
      "main": [
        [
          {
            "node": "응답 반환",
            "type": "main",
            "index": 0
          }
        ]
      ]
    }
  },
  "active": false,
  "settings": {
    "executionOrder": "v1"
  },
  "tags": [
    {
      "name": "autus",
      "id": "autus-tag"
    }
  ]
}

{
  "name": "피드백 수집 및 시너지 보정",
  "nodes": [
    {
      "parameters": {
        "httpMethod": "POST",
        "path": "feedback",
        "responseMode": "responseNode",
        "options": {}
      },
      "id": "feedback-webhook",
      "name": "피드백 Webhook",
      "type": "n8n-nodes-base.webhook",
      "typeVersion": 2,
      "position": [250, 300]
    },
    {
      "parameters": {
        "jsCode": "const data = $input.first().json;\n\n// 피드백 검증\nif (!data.automation_id || data.rating === undefined) {\n  throw new Error('automation_id와 rating은 필수입니다.');\n}\n\n// rating: 1 (긍정), -1 (부정)\nconst rating = data.rating > 0 ? 1 : -1;\n\n// 시너지율 조정 계산\n// 긍정: +2%, 부정: -5%\nconst synergyAdjustment = rating === 1 ? 0.02 : -0.05;\n\nreturn [{\n  json: {\n    automation_id: data.automation_id,\n    rating,\n    comment: data.comment || '',\n    synergy_adjustment: synergyAdjustment,\n    processed_at: new Date().toISOString()\n  }\n}];"
      },
      "id": "process-feedback",
      "name": "피드백 처리",
      "type": "n8n-nodes-base.code",
      "typeVersion": 2,
      "position": [450, 300]
    },
    {
      "parameters": {
        "method": "POST",
        "url": "={{$env.AUTUS_API_URL}}/api/feedback",
        "sendBody": true,
        "bodyParameters": {
          "parameters": [
            {
              "name": "automation_id",
              "value": "={{ $json.automation_id }}"
            },
            {
              "name": "rating",
              "value": "={{ $json.rating }}"
            },
            {
              "name": "comment",
              "value": "={{ $json.comment }}"
            },
            {
              "name": "synergy_adjustment",
              "value": "={{ $json.synergy_adjustment }}"
            }
          ]
        },
        "options": {}
      },
      "id": "save-feedback",
      "name": "피드백 저장",
      "type": "n8n-nodes-base.httpRequest",
      "typeVersion": 4.2,
      "position": [650, 300]
    },
    {
      "parameters": {
        "method": "PATCH",
        "url": "={{$env.AUTUS_API_URL}}/api/automations/{{ $json.automation_id }}/synergy",
        "sendBody": true,
        "bodyParameters": {
          "parameters": [
            {
              "name": "adjustment",
              "value": "={{ $json.synergy_adjustment }}"
            }
          ]
        },
        "options": {}
      },
      "id": "update-synergy",
      "name": "시너지율 업데이트",
      "type": "n8n-nodes-base.httpRequest",
      "typeVersion": 4.2,
      "position": [850, 300]
    },
    {
      "parameters": {
        "conditions": {
          "options": {
            "caseSensitive": true,
            "leftValue": "",
            "typeValidation": "strict"
          },
          "conditions": [
            {
              "id": "rating-check",
              "leftValue": "={{ $json.rating }}",
              "rightValue": -1,
              "operator": {
                "type": "number",
                "operation": "equals"
              }
            }
          ]
        }
      },
      "id": "check-negative",
      "name": "부정 피드백?",
      "type": "n8n-nodes-base.if",
      "typeVersion": 2,
      "position": [1050, 300]
    },
    {
      "parameters": {
        "channel": "#autus-alerts",
        "text": "=⚠️ 부정 피드백 수신\n\n*자동화 ID:* {{ $json.automation_id }}\n*코멘트:* {{ $json.comment }}\n*시너지 조정:* {{ $json.synergy_adjustment }}",
        "otherOptions": {}
      },
      "id": "slack-alert",
      "name": "Slack 경고",
      "type": "n8n-nodes-base.slack",
      "typeVersion": 2.2,
      "position": [1250, 200]
    },
    {
      "parameters": {
        "respondWith": "json",
        "responseBody": "={{ { success: true, message: '피드백 처리 완료', synergy_adjustment: $json.synergy_adjustment } }}",
        "options": {}
      },
      "id": "respond",
      "name": "응답 반환",
      "type": "n8n-nodes-base.respondToWebhook",
      "typeVersion": 1.1,
      "position": [1250, 400]
    }
  ],
  "connections": {
    "피드백 Webhook": {
      "main": [
        [
          {
            "node": "피드백 처리",
            "type": "main",
            "index": 0
          }
        ]
      ]
    },
    "피드백 처리": {
      "main": [
        [
          {
            "node": "피드백 저장",
            "type": "main",
            "index": 0
          }
        ]
      ]
    },
    "피드백 저장": {
      "main": [
        [
          {
            "node": "시너지율 업데이트",
            "type": "main",
            "index": 0
          }
        ]
      ]
    },
    "시너지율 업데이트": {
      "main": [
        [
          {
            "node": "부정 피드백?",
            "type": "main",
            "index": 0
          }
        ]
      ]
    },
    "부정 피드백?": {
      "main": [
        [
          {
            "node": "Slack 경고",
            "type": "main",
            "index": 0
          }
        ],
        [
          {
            "node": "응답 반환",
            "type": "main",
            "index": 0
          }
        ]
      ]
    },
    "Slack 경고": {
      "main": [
        [
          {
            "node": "응답 반환",
            "type": "main",
            "index": 0
          }
        ]
      ]
    }
  },
  "active": false,
  "settings": {
    "executionOrder": "v1"
  },
  "tags": [
    {
      "name": "autus",
      "id": "autus-tag"
    }
  ]
}

{
  "name": "피드백 수집 및 시너지 보정",
  "nodes": [
    {
      "parameters": {
        "httpMethod": "POST",
        "path": "feedback",
        "responseMode": "responseNode",
        "options": {}
      },
      "id": "feedback-webhook",
      "name": "피드백 Webhook",
      "type": "n8n-nodes-base.webhook",
      "typeVersion": 2,
      "position": [250, 300]
    },
    {
      "parameters": {
        "jsCode": "const data = $input.first().json;\n\n// 피드백 검증\nif (!data.automation_id || data.rating === undefined) {\n  throw new Error('automation_id와 rating은 필수입니다.');\n}\n\n// rating: 1 (긍정), -1 (부정)\nconst rating = data.rating > 0 ? 1 : -1;\n\n// 시너지율 조정 계산\n// 긍정: +2%, 부정: -5%\nconst synergyAdjustment = rating === 1 ? 0.02 : -0.05;\n\nreturn [{\n  json: {\n    automation_id: data.automation_id,\n    rating,\n    comment: data.comment || '',\n    synergy_adjustment: synergyAdjustment,\n    processed_at: new Date().toISOString()\n  }\n}];"
      },
      "id": "process-feedback",
      "name": "피드백 처리",
      "type": "n8n-nodes-base.code",
      "typeVersion": 2,
      "position": [450, 300]
    },
    {
      "parameters": {
        "method": "POST",
        "url": "={{$env.AUTUS_API_URL}}/api/feedback",
        "sendBody": true,
        "bodyParameters": {
          "parameters": [
            {
              "name": "automation_id",
              "value": "={{ $json.automation_id }}"
            },
            {
              "name": "rating",
              "value": "={{ $json.rating }}"
            },
            {
              "name": "comment",
              "value": "={{ $json.comment }}"
            },
            {
              "name": "synergy_adjustment",
              "value": "={{ $json.synergy_adjustment }}"
            }
          ]
        },
        "options": {}
      },
      "id": "save-feedback",
      "name": "피드백 저장",
      "type": "n8n-nodes-base.httpRequest",
      "typeVersion": 4.2,
      "position": [650, 300]
    },
    {
      "parameters": {
        "method": "PATCH",
        "url": "={{$env.AUTUS_API_URL}}/api/automations/{{ $json.automation_id }}/synergy",
        "sendBody": true,
        "bodyParameters": {
          "parameters": [
            {
              "name": "adjustment",
              "value": "={{ $json.synergy_adjustment }}"
            }
          ]
        },
        "options": {}
      },
      "id": "update-synergy",
      "name": "시너지율 업데이트",
      "type": "n8n-nodes-base.httpRequest",
      "typeVersion": 4.2,
      "position": [850, 300]
    },
    {
      "parameters": {
        "conditions": {
          "options": {
            "caseSensitive": true,
            "leftValue": "",
            "typeValidation": "strict"
          },
          "conditions": [
            {
              "id": "rating-check",
              "leftValue": "={{ $json.rating }}",
              "rightValue": -1,
              "operator": {
                "type": "number",
                "operation": "equals"
              }
            }
          ]
        }
      },
      "id": "check-negative",
      "name": "부정 피드백?",
      "type": "n8n-nodes-base.if",
      "typeVersion": 2,
      "position": [1050, 300]
    },
    {
      "parameters": {
        "channel": "#autus-alerts",
        "text": "=⚠️ 부정 피드백 수신\n\n*자동화 ID:* {{ $json.automation_id }}\n*코멘트:* {{ $json.comment }}\n*시너지 조정:* {{ $json.synergy_adjustment }}",
        "otherOptions": {}
      },
      "id": "slack-alert",
      "name": "Slack 경고",
      "type": "n8n-nodes-base.slack",
      "typeVersion": 2.2,
      "position": [1250, 200]
    },
    {
      "parameters": {
        "respondWith": "json",
        "responseBody": "={{ { success: true, message: '피드백 처리 완료', synergy_adjustment: $json.synergy_adjustment } }}",
        "options": {}
      },
      "id": "respond",
      "name": "응답 반환",
      "type": "n8n-nodes-base.respondToWebhook",
      "typeVersion": 1.1,
      "position": [1250, 400]
    }
  ],
  "connections": {
    "피드백 Webhook": {
      "main": [
        [
          {
            "node": "피드백 처리",
            "type": "main",
            "index": 0
          }
        ]
      ]
    },
    "피드백 처리": {
      "main": [
        [
          {
            "node": "피드백 저장",
            "type": "main",
            "index": 0
          }
        ]
      ]
    },
    "피드백 저장": {
      "main": [
        [
          {
            "node": "시너지율 업데이트",
            "type": "main",
            "index": 0
          }
        ]
      ]
    },
    "시너지율 업데이트": {
      "main": [
        [
          {
            "node": "부정 피드백?",
            "type": "main",
            "index": 0
          }
        ]
      ]
    },
    "부정 피드백?": {
      "main": [
        [
          {
            "node": "Slack 경고",
            "type": "main",
            "index": 0
          }
        ],
        [
          {
            "node": "응답 반환",
            "type": "main",
            "index": 0
          }
        ]
      ]
    },
    "Slack 경고": {
      "main": [
        [
          {
            "node": "응답 반환",
            "type": "main",
            "index": 0
          }
        ]
      ]
    }
  },
  "active": false,
  "settings": {
    "executionOrder": "v1"
  },
  "tags": [
    {
      "name": "autus",
      "id": "autus-tag"
    }
  ]
}

















